{"id":57841,"number":38,"podcast_id":2597,"guid":"http://www.themadboxworld.com/?post_type=podcast&p=162","title":"035: Clefairy","author":"Chris Taylor","duration":356,"explicit":true,"published":true,"description":"Are you ready to party? ARE YOU READY TO PARTY? Well com’mon over to the Clefairy block party – we gon’ skip, hop and pop rocks till the moon is up!  \r\n\r\nHosts: [Chris](https://twitter.com/DaLiquidSword), [Aleksandar](https://www.youtube.com/channel/UC56emXYp1pHXL2E9SLcYisw), [Ethan](https://twitter.com/SynSpawn), [Mark](https://www.twitch.tv/robobobatron)\r\n\r\nFor more episodes and the full ranking list visit [Magmar Sucks](http://www.magmarsucks.com) on the web.\r\n\r\nFor more on the Pokemon in this episode check out their [Bulbapedia page](http://bulbapedia.bulbagarden.net/wiki/Clefairy_(Pokémon))","long_description":"Are you ready to party? ARE YOU READY TO PARTY? Well com’mon over to the Clefairy block party – we gon’ skip, hop and pop rocks till the moon is up!  \r\n\r\nHosts: [Chris](https://twitter.com/DaLiquidSword), [Aleksandar](https://www.youtube.com/channel/UC56emXYp1pHXL2E9SLcYisw), [Ethan](https://twitter.com/SynSpawn), [Mark](https://www.twitch.tv/robobobatron)\r\n\r\nFor more episodes and the full ranking list visit [Magmar Sucks](http://www.magmarsucks.com) on the web.\r\n\r\nFor more on the Pokemon in this episode check out their [Bulbapedia page](http://bulbapedia.bulbagarden.net/wiki/Clefairy_(Pokémon))\r\n","published_at":"2016-08-07T21:55:00.000-07:00","audio_file_size":5889010,"audio_url":"http://audio.simplecast.com/57841.mp3","sharing_url":"https://simplecast.com/s/35d57b39","images":{"large":"https://media.simplecast.com/episode/image/57841/1484682593-artwork.jpg","small":"https://media.simplecast.com/episode/image/57841/small_1484682593-artwork.jpg","thumb":"https://media.simplecast.com/episode/image/57841/thumb_1484682593-artwork.jpg"},"sponsors":[]}